statisticdistribution/Binomialdistribution.py
statisticdistribution/Gaussiandistribution.py
statisticdistribution/Generaldistribution.py
statisticdistribution/__init__.py
statisticdistribution-0.1.dist-info/METADATA
statisticdistribution-0.1.dist-info/WHEEL
statisticdistribution-0.1.dist-info/top_level.txt
statisticdistribution-0.1.dist-info/RECORD
