Metadata-Version: 2.1
Name: statisticdistribution
Version: 0.1
Summary: Gaussian and binomial distributions
Home-page: UNKNOWN
Author: Luter .C. Aondona
License: UNKNOWN
Platform: UNKNOWN
